miniscript/__init__.py
miniscript/_context.py
miniscript/_engine.py
miniscript/_task.py
miniscript/_types.py
miniscript/_utils.py
miniscript/filters.py
miniscript/tasks.py
miniscript/tests/__init__.py
miniscript/tests/ansible_bug_11891.yaml
miniscript/tests/example-docs.yaml
miniscript/tests/example-large.yaml
miniscript/tests/test_context.py
miniscript/tests/test_engine.py
miniscript/tests/test_filters.py
miniscript/tests/test_functional.py
miniscript/tests/test_task.py
miniscript/tests/test_tasks.py
miniscript/tests/test_utils.py
miniscript-1.1.0.dist-info/LICENSE.rst
miniscript-1.1.0.dist-info/METADATA
miniscript-1.1.0.dist-info/WHEEL
miniscript-1.1.0.dist-info/pbr.json
miniscript-1.1.0.dist-info/top_level.txt
miniscript-1.1.0.dist-info/RECORD
