Metadata-Version: 2.1
Name: miniscript
Version: 1.1.0
Summary: Scripting Language with Ansible-like Syntax
Home-page: https://miniscript.readthedocs.io/en/latest/
Author: Dmitry Tantsur
Author-email: dtantsur@protonmail.com
License: BSD-3-Clause
Platform: UNKNOWN
Classifier: Intended Audience :: Developers
Classifier: Intended Audience :: Information Technology
Classifier: License :: OSI Approved :: BSD License
Classifier: Operating System :: OS Independent
Classifier: Programming Language :: Python
Classifier: Programming Language :: Python :: 3 :: Only
Classifier: Programming Language :: Python :: 3
Classifier: Programming Language :: Python :: 3.6
Classifier: Programming Language :: Python :: 3.7
Classifier: Programming Language :: Python :: 3.8
Classifier: Programming Language :: Python :: 3.9
Requires-Python: >=3.6
Requires-Dist: jinja2 (>=2.11.2)
Provides-Extra: extras
Requires-Dist: jmespath ; extra == 'extras'
